[
    {
        "name":  "loki",
        "status":  "SKIPPED",
        "pid":  null,
        "binary":  "",
        "note":  "binary not found (set LOKI_BIN or install command)",
        "healthUrl":  "http://127.0.0.1:3100/ready"
    },
    {
        "name":  "promtail",
        "status":  "SKIPPED",
        "pid":  null,
        "binary":  "",
        "note":  "binary not found (set PROMTAIL_BIN or install command)",
        "healthUrl":  ""
    },
    {
        "name":  "prometheus",
        "status":  "SKIPPED",
        "pid":  null,
        "binary":  "",
        "note":  "binary not found (set PROMETHEUS_BIN or install command)",
        "healthUrl":  "http://127.0.0.1:9090/-/ready"
    },
    {
        "name":  "tempo",
        "status":  "SKIPPED",
        "pid":  null,
        "binary":  "",
        "note":  "binary not found (set TEMPO_BIN or install command)",
        "healthUrl":  "http://127.0.0.1:3200/ready"
    },
    {
        "name":  "otel-collector",
        "status":  "SKIPPED",
        "pid":  null,
        "binary":  "",
        "note":  "binary not found (set OTEL_BIN or install command)",
        "healthUrl":  "http://127.0.0.1:13133/"
    },
    {
        "name":  "alertmanager",
        "status":  "SKIPPED",
        "pid":  null,
        "binary":  "",
        "note":  "binary not found (set ALERTMANAGER_BIN or install command)",
        "healthUrl":  "http://127.0.0.1:9093/-/ready"
    },
    {
        "name":  "grafana",
        "status":  "SKIPPED",
        "pid":  null,
        "binary":  "",
        "note":  "binary not found (set GRAFANA_BIN or install command)",
        "healthUrl":  "http://127.0.0.1:3000/api/health"
    }
]
